<?xml version="1.0" encoding="UTF-8"?>
<Patch>
    <Operation Class="PatchOperationAdd">
        <xpath>Defs</xpath>
        <value>
            <AK_Dll.OperatorDef>
                <name>Aru</name>
                <surname>Rikuhachima</surname>
                <nickname>Aru</nickname>
                <childHood>Club_PS68</childHood>
                <adultHood/>
                <abilities/>
                <age>16</age>
                <isMale>false</isMale>
                <hediffInate/>
                <voicePackDef/>
                <relations/>
                <traits/>
                <weapon>BAW_Aru</weapon>
                <apparels/>
                <items/>
                <bodyTypeDef>Female</bodyTypeDef>
                <skinColor/>
                <hairColor/>
                <hair/>
                <beard/>
                <operatorType>RA_OperatorClass_Gehenna</operatorType>
                <stand>Portraits/Normal/Aru</stand>
                <standOffset/>
                <standRatio/>
                <headPortrait>Icons/Aru</headPortrait>
                <headPortraitOffset/>
                <defName>RA_Aru</defName>
                <label>Aru</label>
                <description>Aru</description>
                <descriptionHyperlinks/>
                <ignoreConfigErrors>false</ignoreConfigErrors>
                <skills>
                    <li>
                        <skill>Animals</skill>
                        <level>3</level>
                        <fireLevel>0</fireLevel>
                    </li>
                    <li>
                        <skill>Artistic</skill>
                        <level>5</level>
                        <fireLevel>0</fireLevel>
                    </li>
                    <li>
                        <skill>Construction</skill>
                        <level>10</level>
                        <fireLevel>2</fireLevel>
                    </li>
                    <li>
                        <skill>Cooking</skill>
                        <level>2</level>
                        <fireLevel>0</fireLevel>
                    </li>
                    <li>
                        <skill>Crafting</skill>
                        <level>6</level>
                        <fireLevel>1</fireLevel>
                    </li>
                    <li>
                        <skill>Intellectual</skill>
                        <level>10</level>
                        <fireLevel>2</fireLevel>
                    </li>
                    <li>
                        <skill>Medicine</skill>
                        <level>2</level>
                        <fireLevel>0</fireLevel>
                    </li>
                    <li>
                        <skill>Melee</skill>
                        <level>4</level>
                        <fireLevel>1</fireLevel>
                    </li>
                    <li>
                        <skill>Mining</skill>
                        <level>0</level>
                        <fireLevel>1</fireLevel>
                    </li>
                    <li>
                        <skill>Plants</skill>
                        <level>2</level>
                        <fireLevel>0</fireLevel>
                    </li>
                    <li>
                        <skill>Shooting</skill>
                        <level>12</level>
                        <fireLevel>2</fireLevel>
                    </li>
                    <li>
                        <skill>Social</skill>
                        <level>6</level>
                        <fireLevel>1</fireLevel>
                    </li>
                </skills>
            </AK_Dll.OperatorDef>
        </value>
    </Operation>
</Patch>